setup.py
pg_store/__init__.py
pg_store/store.py
pg_store/tests.py
pulsar_postgresql.egg-info/PKG-INFO
pulsar_postgresql.egg-info/SOURCES.txt
pulsar_postgresql.egg-info/dependency_links.txt
pulsar_postgresql.egg-info/requires.txt
pulsar_postgresql.egg-info/top_level.txt