Metadata-Version: 1.1
Name: pulsar-postgresql
Version: 0.1.0
Summary: Pulsar store for postgresql database based on aiopg
Home-page: https://github.com/scailer/pulsar-postgresql
Author: Dmitriy Vlasov
Author-email: scailer@yandex.ru
License: MIT license
Platform: UNKNOWN
Classifier: Development Status :: 4 - Beta
Classifier: Environment :: Plugins
Classifier: Intended Audience :: Developers
Classifier: License :: OSI Approved :: MIT License
Classifier: Programming Language :: Python
Classifier: Programming Language :: Python :: 3
Classifier: Programming Language :: Python :: 3.5
Classifier: Topic :: Software Development :: Libraries :: Python Modules
Requires: aiopg
Requires: pulsar (>= 1.4.0)
